exchanges_wrapper/__init__.py
exchanges_wrapper/client.py
exchanges_wrapper/definitions.py
exchanges_wrapper/errors.py
exchanges_wrapper/events.py
exchanges_wrapper/exch_srv.py
exchanges_wrapper/exch_srv_cfg.toml.template
exchanges_wrapper/http_client.py
exchanges_wrapper/lib.py
exchanges_wrapper/web_sockets.py
exchanges_wrapper/martin/__init__.py
exchanges_wrapper/parsers/bitfinex.py
exchanges_wrapper/parsers/bybit.py
exchanges_wrapper/parsers/huobi.py
exchanges_wrapper/parsers/okx.py
exchanges_wrapper/proto/martin.proto
exchanges_wrapper-2.1.46.dist-info/entry_points.txt
exchanges_wrapper-2.1.46.dist-info/licenses/LICENSE.md
exchanges_wrapper-2.1.46.dist-info/WHEEL
exchanges_wrapper-2.1.46.dist-info/METADATA
exchanges_wrapper-2.1.46.dist-info/RECORD
