Metadata-Version: 2.4
Name: exchanges-wrapper
Version: 2.1.46
Summary: REST API and WebSocket asyncio wrapper with grpc powered multiplexer server
Author-email: Thomas Marchand <thomas.marchand@tuta.io>, Jerry Fedorenko <jerry.fedorenko@yahoo.com>
Requires-Python: >=3.10
Classifier: Programming Language :: Python :: 3
Classifier: Development Status :: 5 - Production/Stable
Classifier: License :: OSI Approved :: MIT License
Classifier: Operating System :: Unix
Classifier: Operating System :: Microsoft :: Windows
Classifier: Operating System :: MacOS
License-File: LICENSE.md
Requires-Dist: crypto-ws-api==2.1.6
Requires-Dist: pyotp==2.9.0
Requires-Dist: simplejson==3.20.2
Requires-Dist: aiohttp~=3.13.3
Requires-Dist: expiringdict~=1.2.2
Requires-Dist: betterproto==2.0.0b7
Requires-Dist: grpclib~=0.4.8
Project-URL: Source, https://github.com/DogsTailFarmer/exchanges-wrapper
